flask_pyctuator/__init__.py
flask_pyctuator/flask_pyctuator.py
flask_pyctuator-0.1.1.dist-info/LICENSE
flask_pyctuator-0.1.1.dist-info/WHEEL
flask_pyctuator-0.1.1.dist-info/METADATA
flask_pyctuator-0.1.1.dist-info/RECORD
