Metadata-Version: 2.1
Name: flask-pyctuator
Version: 0.1.1
Summary: Flask Extension for using Pyctuator to enable Spring Boot Admin (SBA) to monitor the application, see https://github.com/SolarEdgeTech/pyctuator
Home-page: https://github.com/SolarEdgeTech/flask-pyctuator
Keywords: spring boot admin,actuator,pyctuator,flask
Author: michael.yak
Author-email: michael.yakobi@solaredge.com
Requires-Python: >=3.7,<4.0
Classifier: Development Status :: 4 - Beta
Classifier: Environment :: Web Environment
Classifier: Framework :: Flask
Classifier: Intended Audience :: Developers
Classifier: License :: OSI Approved :: Apache Software License
Classifier: Programming Language :: Python :: 3
Classifier: Programming Language :: Python :: 3.7
Classifier: Programming Language :: Python :: 3.8
Classifier: Programming Language :: Python :: 3.9
Classifier: Topic :: Internet :: WWW/HTTP :: HTTP Servers
Classifier: Topic :: Internet :: WWW/HTTP :: WSGI :: Application
Classifier: Topic :: Software Development :: Libraries :: Python Modules
Classifier: Topic :: System :: Monitoring
Classifier: Typing :: Typed
Provides-Extra: db
Provides-Extra: psutil
Provides-Extra: redis
Requires-Dist: flask (>=1.1,<2.0)
Requires-Dist: pyctuator (>=0.17.0,<0.18.0)
Project-URL: Repository, https://github.com/SolarEdgeTech/flask-pyctuator
